labcams/__init__.py
labcams/avt.py
labcams/basler.py
labcams/cam_stim_trigger.py
labcams/cams.py
labcams/gui.py
labcams/io.py
labcams/nidaq_acq.py
labcams/pco.py
labcams/plugins.py
labcams/pointgreycam.py
labcams/pvcam.py
labcams/qimaging.py
labcams/qimaging_dll.py
labcams/utils.py
labcams/widgets.py
labcams/ximeacam.py
labcams-0.7.2.dist-info/licenses/LICENSE.txt
labcams-0.7.2.dist-info/METADATA
labcams-0.7.2.dist-info/WHEEL
labcams-0.7.2.dist-info/entry_points.txt
labcams-0.7.2.dist-info/top_level.txt
labcams-0.7.2.dist-info/RECORD
