Metadata-Version: 2.4
Name: labcams
Version: 0.7.2
Summary: Multicamera video acquisition,online compression and automation
Home-page: https://github.com/jcouto/labcams
Author: Joao Couto
Author-email: jpcouto@gmail.com
License: GPL
Requires-Python: >=3.8
License-File: LICENSE.txt
Requires-Dist: numpy
Requires-Dist: scipy
Requires-Dist: pandas
Requires-Dist: tqdm
Requires-Dist: pyzmq
Requires-Dist: opencv-python-headless
Requires-Dist: tifffile
Requires-Dist: pyqt5
Requires-Dist: pyqtgraph
Requires-Dist: pillow
Requires-Dist: scikit-video
Requires-Dist: pyserial
Requires-Dist: natsort
Dynamic: author
Dynamic: author-email
Dynamic: description
Dynamic: description-content-type
Dynamic: home-page
Dynamic: license
Dynamic: license-file
Dynamic: requires-dist
Dynamic: requires-python
Dynamic: summary
